README.md
setup.py
xiyang_morph/__init__.py
xiyang_morph/config.py
xiyang_morph/face_detect_and_track.py
xiyang_morph/face_detection.py
xiyang_morph/face_points_detection.py
xiyang_morph/face_swap.py
xiyang_morph/morph.py
xiyang_morph/video_handler.py
xiyang_morph/models/haarcascade_frontalface_default.xml
xiyang_morph/models/shape_predictor_68_face_landmarks.dat
xiyang_morph/models/shape_predictor_81_face_landmarks.dat
xiyang_morph_pkg.egg-info/PKG-INFO
xiyang_morph_pkg.egg-info/SOURCES.txt
xiyang_morph_pkg.egg-info/dependency_links.txt
xiyang_morph_pkg.egg-info/requires.txt
xiyang_morph_pkg.egg-info/top_level.txt